machine_learning/__init__.py
machine_learning/evaluation/__init__.py
machine_learning/evaluation/default_evaluation_service.py
machine_learning/evaluation/abstractions/__init__.py
machine_learning/evaluation/abstractions/default_evaluation_plugin.py
machine_learning/evaluation/abstractions/evaluation_metric.py
machine_learning/evaluation/abstractions/evaluation_service.py
machine_learning/evaluation/abstractions/multi_metric.py
machine_learning/evaluation/contexts/__init__.py
machine_learning/evaluation/contexts/evaluation_context.py
machine_learning/evaluation/contexts/multi_evaluation_context.py
machine_learning/exceptions/__init__.py
machine_learning/modeling/__init__.py
machine_learning/modeling/pytorch_model.py
machine_learning/modeling/abstractions/__init__.py
machine_learning/modeling/abstractions/model.py
machine_learning/modeling/adapter/__init__.py
machine_learning/modeling/adapter/sklearn_estimator_adapter.py
machine_learning/operators/__init__.py
machine_learning/operators/true_division.py
machine_learning/tests/__init__.py
machine_learning/tests/batch_training_service_tests.py
machine_learning/tests/default_evaluation_service_tests.py
machine_learning/training/__init__.py
machine_learning/training/batch_training_service.py
machine_learning/training/custom_stop_condition.py
machine_learning/training/default_pytorch_training.py
machine_learning/training/abstractions/__init__.py
machine_learning/training/abstractions/batch_training_plugin.py
machine_learning/training/abstractions/stop_condition.py
machine_learning/training/abstractions/training_service.py
machine_learning_ChrisPrein-9.0.1.dist-info/LICENSE
machine_learning_ChrisPrein-9.0.1.dist-info/METADATA
machine_learning_ChrisPrein-9.0.1.dist-info/WHEEL
machine_learning_ChrisPrein-9.0.1.dist-info/top_level.txt
machine_learning_ChrisPrein-9.0.1.dist-info/RECORD
